buf/validate/expression_pb2.py
buf/validate/expression_pb2.pyi
buf/validate/expression_pb2_grpc.py
buf/validate/validate_pb2.py
buf/validate/validate_pb2.pyi
buf/validate/validate_pb2_grpc.py
buf/validate/priv/private_pb2.py
buf/validate/priv/private_pb2.pyi
buf/validate/priv/private_pb2_grpc.py
google/api/annotations_pb2.py
google/api/annotations_pb2.pyi
google/api/annotations_pb2_grpc.py
google/api/field_behavior_pb2.py
google/api/field_behavior_pb2.pyi
google/api/field_behavior_pb2_grpc.py
google/api/http_pb2.py
google/api/http_pb2.pyi
google/api/http_pb2_grpc.py
kessel/__init__.py
kessel/auth/__init__.py
kessel/auth/auth.py
kessel/grpc/__init__.py
kessel/inventory/__init__.py
kessel/inventory/v1/__init__.py
kessel/inventory/v1/health_pb2.py
kessel/inventory/v1/health_pb2.pyi
kessel/inventory/v1/health_pb2_grpc.py
kessel/inventory/v1beta1/authz/check_pb2.py
kessel/inventory/v1beta1/authz/check_pb2.pyi
kessel/inventory/v1beta1/authz/check_pb2_grpc.py
kessel/inventory/v1beta1/authz/common_pb2.py
kessel/inventory/v1beta1/authz/common_pb2.pyi
kessel/inventory/v1beta1/authz/common_pb2_grpc.py
kessel/inventory/v1beta1/relationships/k8spolicy_ispropagatedto_k8scluster_detail_pb2.py
kessel/inventory/v1beta1/relationships/k8spolicy_ispropagatedto_k8scluster_detail_pb2.pyi
kessel/inventory/v1beta1/relationships/k8spolicy_ispropagatedto_k8scluster_detail_pb2_grpc.py
kessel/inventory/v1beta1/relationships/k8spolicy_ispropagatedto_k8scluster_pb2.py
kessel/inventory/v1beta1/relationships/k8spolicy_ispropagatedto_k8scluster_pb2.pyi
kessel/inventory/v1beta1/relationships/k8spolicy_ispropagatedto_k8scluster_pb2_grpc.py
kessel/inventory/v1beta1/relationships/k8spolicy_ispropagatedto_k8scluster_service_pb2.py
kessel/inventory/v1beta1/relationships/k8spolicy_ispropagatedto_k8scluster_service_pb2.pyi
kessel/inventory/v1beta1/relationships/k8spolicy_ispropagatedto_k8scluster_service_pb2_grpc.py
kessel/inventory/v1beta1/relationships/metadata_pb2.py
kessel_sdk-2.0.1.dist-info/licenses/LICENSE
kessel_sdk-2.0.1.dist-info/METADATA
kessel_sdk-2.0.1.dist-info/WHEEL
kessel_sdk-2.0.1.dist-info/top_level.txt
kessel_sdk-2.0.1.dist-info/RECORD
