Metadata-Version: 2.4
Name: kessel-sdk
Version: 2.0.1
Summary: Client SDK for Kessel.
Project-URL: Homepage, https://project-kessel.github.io/docs/
Project-URL: Issues, https://github.com/project-kessel/kessel-sdk-py
Classifier: Programming Language :: Python :: 3
Classifier: Operating System :: OS Independent
Requires-Python: >=3.11
License-File: LICENSE
Requires-Dist: protobuf<6.34.0,>=6.31.1
Requires-Dist: types-protobuf~=6.30
Requires-Dist: grpcio
Provides-Extra: auth
Requires-Dist: google-auth; extra == "auth"
Requires-Dist: requests-oauthlib; extra == "auth"
Requires-Dist: requests; extra == "auth"
Provides-Extra: dev
Requires-Dist: flake8>=6.0.0; extra == "dev"
Requires-Dist: black; extra == "dev"
Dynamic: license-file
